aiobinance/__init__.py
aiobinance/client.py
aiobinance/exceptions.py
aiobinance/modules/account.py
aiobinance/modules/base.py
aiobinance/modules/general.py
aiobinance/modules/market.py
aiobinance/modules/stream.py
aiobinance/network.py
aiobinance/tests/__init__.py
aiobinance/tests/test_client.py
aiobinance/tests/test_utils.py
aiobinance/types.py
aiobinance/utils.py
aiobinance-0.1.1.dist-info/WHEEL
aiobinance-0.1.1.dist-info/METADATA
aiobinance-0.1.1.dist-info/RECORD
