Metadata-Version: 2.1
Name: aiobinance
Version: 0.1.1
Summary: Binance API async Python wrapper
License: MIT
Author: ape364
Author-email: ape364@gmail.com
Requires-Python: >=3.7,<4.0
Classifier: License :: OSI Approved :: MIT License
Classifier: Programming Language :: Python :: 3
Classifier: Programming Language :: Python :: 3.7
Requires-Dist: aiohttp (>=3.5,<4.0)
